biotmed_organization_sdk/__init__.py
biotmed_organization_sdk/api_client.py
biotmed_organization_sdk/api_response.py
biotmed_organization_sdk/configuration.py
biotmed_organization_sdk/exceptions.py
biotmed_organization_sdk/py.typed
biotmed_organization_sdk/rest.py
biotmed_organization_sdk/api/__init__.py
biotmed_organization_sdk/api/built_in_templates_api_api.py
biotmed_organization_sdk/api/caregiver_api_api.py
biotmed_organization_sdk/api/health_check_api_api.py
biotmed_organization_sdk/api/internal_entity_api_api.py
biotmed_organization_sdk/api/invitation_api_api.py
biotmed_organization_sdk/api/landing_page_api_api.py
biotmed_organization_sdk/api/organization_api_api.py
biotmed_organization_sdk/api/organization_user_api_api.py
biotmed_organization_sdk/api/patient_alert_api_api.py
biotmed_organization_sdk/api/patient_api_api.py
biotmed_organization_sdk/api/registration_code_api_api.py
biotmed_organization_sdk/api/sync_token_permissions_core_api_api.py
biotmed_organization_sdk/api/temporary_token_operation_api_api.py
biotmed_organization_sdk/api/user_api_api.py
biotmed_organization_sdk/models/__init__.py
biotmed_organization_sdk/models/address.py
biotmed_organization_sdk/models/address_update_request.py
biotmed_organization_sdk/models/basic_entity_data.py
biotmed_organization_sdk/models/basic_organization_response.py
biotmed_organization_sdk/models/basic_referenced_entity_data_uuidid.py
biotmed_organization_sdk/models/basic_template_data.py
biotmed_organization_sdk/models/built_in_data_status.py
biotmed_organization_sdk/models/built_in_template_props.py
biotmed_organization_sdk/models/built_in_templates_response.py
biotmed_organization_sdk/models/caregiver_response.py
biotmed_organization_sdk/models/create_alert_by_template_name_request.py
biotmed_organization_sdk/models/create_alert_request.py
biotmed_organization_sdk/models/create_caregiver_by_template_name_request.py
biotmed_organization_sdk/models/create_caregiver_request.py
biotmed_organization_sdk-0.1.0.dist-info/METADATA
biotmed_organization_sdk-0.1.0.dist-info/WHEEL
biotmed_organization_sdk-0.1.0.dist-info/top_level.txt
biotmed_organization_sdk-0.1.0.dist-info/RECORD
