Metadata-Version: 2.4
Name: biotmed_organization_sdk
Version: 0.1.0
Summary: BioT Organization Service
Home-page: 
Author: OpenAPI Generator community
Author-email: team@openapitools.org
Keywords: OpenAPI,OpenAPI-Generator,BioT Organization Service
Requires-Dist: urllib3<2.1.0,>=1.25.3
Requires-Dist: python-dateutil
Requires-Dist: pydantic>=2
Requires-Dist: typing-extensions>=4.7.1
Dynamic: author
Dynamic: author-email
Dynamic: description
Dynamic: description-content-type
Dynamic: keywords
Dynamic: requires-dist
Dynamic: summary
